LICENSE
README.md
setup.py
olx/__init__.py
olx/partner/__init__.py
olx/partner/advert_logo.py
olx/partner/advert_statistics.py
olx/partner/adverts.py
olx/partner/auth.py
olx/partner/categories_attributes.py
olx/partner/cities_districts.py
olx/partner/languages_currencies.py
olx/partner/models.py
olx/partner/olx.py
olx/partner/paid_features.py
olx/partner/payments.py
olx/partner/threads_messages.py
olx/partner/user_business.py
olx/partner/users.py
olx/public/__init__.py
olx/public/checkout.py
olx/public/graphql.py
olx/public/seo.py
olx/public/utils.py
olx/public/models/__init__.py
olx/public/models/filters.py
olx/public/models/metadata.py
olx/public/models/offers.py
olx/public/models/checkout/__init__.py
olx/public/models/checkout/cost.py
olx/public/models/checkout/listing.py
olx/public/models/seo/__init__.py
olx/public/models/seo/offers.py
olx/public/models/seo/popular_searches.py
olx_api_wrapper.egg-info/PKG-INFO
olx_api_wrapper.egg-info/SOURCES.txt
olx_api_wrapper.egg-info/dependency_links.txt
olx_api_wrapper.egg-info/requires.txt
olx_api_wrapper.egg-info/top_level.txt
tests/__init__.py
tests/test_cities_and_districts.py
tests/test_users.py