Metadata-Version: 2.1
Name: olx-api-wrapper
Version: 1.3.0
Summary: Unofficial Wrapper for OLX API
Home-page: https://github.com/Pawikoski/olx-api-wrapper
Author: Paweł Stawikowski
Author-email: pawikoski@gmail.com
License: MIT
Project-URL: Documentation, https://github.com/Pawikoski/olx-api-wrapper#readme
Project-URL: Issue Tracker, https://github.com/Pawikoski/olx-api-wrapper/issues
Keywords: olx api wrapper unofficial
Classifier: Development Status :: 4 - Beta
Classifier: Programming Language :: Python :: 3.11
Classifier: License :: OSI Approved :: MIT License
Classifier: Operating System :: OS Independent
Requires-Python: >=3.11
License-File: LICENSE
